metatables/__init__.py
metatables/main.py
metatables-0.0.14.dist-info/LICENSE
metatables-0.0.14.dist-info/METADATA
metatables-0.0.14.dist-info/WHEEL
metatables-0.0.14.dist-info/top_level.txt
metatables-0.0.14.dist-info/RECORD
