Metadata-Version: 2.1
Name: metatables
Version: 0.0.14
Summary: Data wrangling on files read with pyreadstat
Author: Joël Grosjean
Author-email: <joel.grosjean@gfs-zh.ch>
Project-URL: Repository, https://github.com/tez4/metatables
Project-URL: Documentation, https://tez4.github.io/metatables/
Keywords: python
Classifier: Development Status :: 1 - Planning
Classifier: Intended Audience :: Developers
Classifier: Programming Language :: Python :: 3
Classifier: Operating System :: OS Independent
Classifier: License :: OSI Approved :: Apache Software License
License-File: LICENSE
Requires-Dist: pyreadstat (>=1.1)
Requires-Dist: pandas (>=1.3)
Provides-Extra: dev
Requires-Dist: pytest (>=3.7) ; extra == 'dev'
Requires-Dist: check-manifest ; extra == 'dev'
Requires-Dist: twine ; extra == 'dev'
Requires-Dist: pdoc3 ; extra == 'dev'
Requires-Dist: flake8 ; extra == 'dev'
Requires-Dist: autopep8 ; extra == 'dev'
